{
    "tasks": [
      {
        "type": "watchvideo",
        "title": "Watch video and earn",
        "content": "",
        "url": ""
      },
      {
        "type": "watchvideo",
        "title": "Watch video and earn",
        "content": "",
        "url": ""
      },
      {
        "type": "nocheck",
        "title": "Play TSUBASA RIVALS",
        "content": "",
        "url": ""
      },
      {
        "type": "nocheck",
        "title": "Join Tassbeeh, earn 30 XP and participate in a $20,000 raffle",
        "content": "",
        "url": ""
      },
      {
        "type": "nocheck",
        "title": "Subscribe to CV Pad Telegram",
        "content": "",
        "url": ""
      }
      {
        "type": "nocheck",
        "title": "Join CV Pad Telegram group",
        "content": "",
        "url": ""
      },
      {
        "type": "nocheck",
        "title": "Play Piggy Bank",
        "content": "",
        "url": ""
      }
      {
        "type": "nocheck",
        "title": "Play Rating",
        "content": "",
        "url": ""
      },
      {
        "type": "nocheck",
        "title": "Follow our CEO on X",
        "content": "",
        "url": ""
      },
      {
        "type": "nocheck",
        "title": "Subscribe to our CEO channel",
        "content": "",
        "url": ""
      },
      {
        "type": "wallet",
        "title": "Connect TON wallet",
        "content": "",
        "url": ""
      },
      {
        "type": "nocheck",
        "title": "Subscribe to trending apps",
        "content": "",
        "url": ""
      },
      {
        "type": "nocheck",
        "title": "Play Trump Farm",
        "content": "",
        "url": ""
      },
      {
        "type": "nocheck",
        "title": "Play 1win token",
        "content": "",
        "url": ""
      },
      {
        "type": "nocheck",
        "title": "Watch the video on our channel",
        "content": "",
        "url": ""
      },
      {
        "type": "nocheck",
        "title": "Subscribe to Whale Channel",
        "content": "",
        "url": "https://t.me/WhAlE_ChAnEl"
      },
      {
        "type": "nocheck",
        "title": "Follow Time Farm on X",
        "content": "",
        "url": ""
      },
      {
        "type": "nocheck",
        "title": "Subscribe to Learn to Earn channel",
        "content": "",
        "url": ""
      },
      {
        "type": "nocheck",
        "title": "Subscribe to Crypto Meme channel",
        "content": "",
        "url": ""
      },
      {
        "type": "nocheck",
        "title": "Subscribe to Crypto Games channel",
        "content": "",
        "url": ""
      },
      {
        "type": "nocheck",
        "title": "Subscribe to TimeFarm channel",
        "content": "",
        "url": ""
      },
      {
        "type": "nocheck",
        "title": "Subscribe to TimeFarm chat",
        "content": "",
        "url": ""
      },
      {
        "type": "nocheck",
        "title": "Subscribe to trending apps",
        "content": "",
        "url": "https://t.me/trendingapps"
      },
      {
        "type": "nocheck",
        "title": "Subscribe to partner - trending apps",
        "content": "",
        "url": "https://t.me/trendingapps"
      }
    ]
  }
  